zensols/garmdown/__init__.py
zensols/garmdown/backup.py
zensols/garmdown/cli.py
zensols/garmdown/config.py
zensols/garmdown/db.py
zensols/garmdown/domain.py
zensols/garmdown/fetcher.py
zensols/garmdown/mng.py
zensols/garmdown/reporter.py
zensols/garmdown/sheets.py
zensols/garmdown/resources/fetch.conf
zensols.garmdown-0.0.8.dist-info/LICENSE.txt
zensols.garmdown-0.0.8.dist-info/METADATA
zensols.garmdown-0.0.8.dist-info/WHEEL
zensols.garmdown-0.0.8.dist-info/entry_points.txt
zensols.garmdown-0.0.8.dist-info/top_level.txt
zensols.garmdown-0.0.8.dist-info/RECORD
