Metadata-Version: 2.1
Name: zensols.garmdown
Version: 0.0.8
Summary: Download Garmin Connect data
Home-page: https://github.com/plandes/garmdown
Author: Paul Landes
Author-email: landes@mailc.net
License: UNKNOWN
Download-URL: https://github.com/plandes/garmdown/releases/download/v0.0.8/zensols.garmdown-0.0.8-py3-none-any.whl
Keywords: garmin data
Platform: UNKNOWN
Requires-Dist: zensols.util (>=1.2.5)
Requires-Dist: Werkzeug (==0.16.0)
Requires-Dist: robobrowser (==0.5.3)
Requires-Dist: oauth2client (>=4.1.3)
Requires-Dist: httplib2 (>=0.12.0)
Requires-Dist: google-api-python-client (>=1.7.7)
Requires-Dist: google-auth (>=1.6.2)
Requires-Dist: google-auth-httplib2 (>=0.0.3)
